optumi_core/__init__.py
optumi_core/_version.py
optumi_core/core.py
optumi_core/exceptions.py
optumi_core/logging.py
optumi_core/login.py
optumi_core/sessions.py
optumi_core/utils.py
optumi_core-3.17.2.dist-info/LICENSE
optumi_core-3.17.2.dist-info/METADATA
optumi_core-3.17.2.dist-info/WHEEL
optumi_core-3.17.2.dist-info/top_level.txt
optumi_core-3.17.2.dist-info/RECORD
